MANIFEST.in
README.md
setup.py
auto_upload/__init__.py
auto_upload/basicinfo.yaml
auto_upload/main.py
auto_upload.egg-info/PKG-INFO
auto_upload.egg-info/SOURCES.txt
auto_upload.egg-info/dependency_links.txt
auto_upload.egg-info/entry_points.txt
auto_upload.egg-info/requires.txt
auto_upload.egg-info/top_level.txt
auto_upload/utils/__init__.py
auto_upload/utils/edittorrent/__init__.py
auto_upload/utils/edittorrent/edittorrent.py
auto_upload/utils/img_upload/__init__.py
auto_upload/utils/img_upload/chevereto.py
auto_upload/utils/img_upload/fapping_emp.py
auto_upload/utils/img_upload/imgbox.py
auto_upload/utils/img_upload/imgupload.py
auto_upload/utils/img_upload/ptpimg.py
auto_upload/utils/img_upload/smms.py
auto_upload/utils/mediafile/__init__.py
auto_upload/utils/mediafile/douban_book.py
auto_upload/utils/mediafile/douban_movie.py
auto_upload/utils/mediafile/doubaninfo.py
auto_upload/utils/mediafile/mediafile.py
auto_upload/utils/para_ctrl/__init__.py
auto_upload/utils/para_ctrl/para_ctrl.py
auto_upload/utils/para_ctrl/readargs.py
auto_upload/utils/para_ctrl/readyaml.py
auto_upload/utils/pathinfo/__init__.py
auto_upload/utils/pathinfo/pathinfo.py
auto_upload/utils/rss_ctrl/__init__.py
auto_upload/utils/seed_machine/__init__.py
auto_upload/utils/seed_machine/seed_machine.py
auto_upload/utils/signer/__init__.py
auto_upload/utils/site/__init__.py
auto_upload/utils/site/site.py
auto_upload/utils/uploader/__init__.py
auto_upload/utils/uploader/audience_upload.py
auto_upload/utils/uploader/auto_upload.py
auto_upload/utils/uploader/carpt_upload.py
auto_upload/utils/uploader/hare_upload.py
auto_upload/utils/uploader/hdfans_upload.py
auto_upload/utils/uploader/hdpt_upload.py
auto_upload/utils/uploader/hdsky_upload.py
auto_upload/utils/uploader/hhclub_upload.py
auto_upload/utils/uploader/lemonhd_upload.py
auto_upload/utils/uploader/piggo_upload.py
auto_upload/utils/uploader/pter_upload.py
auto_upload/utils/uploader/ptnap_upload.py
auto_upload/utils/uploader/ssd_upload.py
auto_upload/utils/uploader/upload_tools.py
auto_upload/utils/uploader/wintersakura_upload.py
auto_upload/utils/web/__init__.py
auto_upload/utils/web/web.py