Metadata-Version: 2.1
Name: auto-upload
Version: 0.0.92
Summary: Upload local resources to PT trackers automatically.
Home-page: https://github.com/dongshuyan/Auto_Upload
Author: sauterne
Author-email: ssauterne@qq.com
License: MIT Licence
Keywords: pip,auto_upload,auto,upload,PT,private tracker
Platform: any
Requires-Python: >=3.7.0
